sqlalchemy_sync_data/__init__.py
sqlalchemy_sync_data/connection.py
sqlalchemy_sync_data/connectors.py
sqlalchemy_sync_data/cursors.py
sqlalchemy_sync_data/getters.py
sqlalchemy_sync_data/handlers.py
sqlalchemy_sync_data/settings.py
sqlalchemy_sync_data/string_key_dict.py
sqlalchemy_sync_data/synchronizator.py
sqlalchemy_sync_data/utils.py
sqlalchemy_sync_data-0.0.1.dist-info/LICENSE
sqlalchemy_sync_data-0.0.1.dist-info/METADATA
sqlalchemy_sync_data-0.0.1.dist-info/WHEEL
sqlalchemy_sync_data-0.0.1.dist-info/RECORD
