Metadata-Version: 2.3
Name: sqlalchemy-sync-data
Version: 0.0.1
Summary: Synchronization of data from different sources into one database using SQLAlchemy as an ORM.
License: Apache-2.0
Author: Sergey V. Elfimov
Author-email: elfimovserg@gmail.com
Requires-Python: >=3.11,<4.0
Classifier: License :: OSI Approved :: Apache Software License
Classifier: Natural Language :: English
Classifier: Operating System :: OS Independent
Classifier: Programming Language :: Python
Classifier: Programming Language :: Python :: 3
Classifier: Programming Language :: Python :: 3.11
Classifier: Programming Language :: Python :: 3.12
Classifier: Programming Language :: Python :: 3.13
Classifier: Programming Language :: Python :: 3 :: Only
Requires-Dist: SQLAlchemy (>=1.4.36,<2.1.0)
Requires-Dist: environs (>=9.3.1)
Requires-Dist: psycopg2 (>=2.9.5)
Requires-Dist: pytz (>=2020.1)
Requires-Dist: requests (>=2.32.3)
Project-URL: Repository, https://github.com/SergeiVElfimov/sqlalchemy-sync-data
